abstract_security/__init__.py
abstract_security/abstract_security.py
abstract_security/envy_it.py
abstract_security/string_clean.py
abstract_security-0.64.dist-info/METADATA
abstract_security-0.64.dist-info/WHEEL
abstract_security-0.64.dist-info/top_level.txt
abstract_security-0.64.dist-info/RECORD
